image_dataset_viz/__init__.py
image_dataset_viz/dataset_exporter.py
image_dataset_viz/fonts/DejaVuSans.ttf
image_dataset_viz-0.2.2.dist-info/METADATA
image_dataset_viz-0.2.2.dist-info/RECORD
image_dataset_viz-0.2.2.dist-info/WHEEL
image_dataset_viz-0.2.2.dist-info/top_level.txt
