Metadata-Version: 2.1
Name: image-dataset-viz
Version: 0.2.2
Summary: Observe dataset of images and targets in few shots
Home-page: https://github.com/vfdev-5/ImageDatasetViz
Author: vfdev-5
Author-email: vfdev.5@gmail.com
License: MIT
Platform: UNKNOWN
Requires-Dist: numpy
Requires-Dist: Pillow
Requires-Dist: tqdm
Requires-Dist: pathlib2; python_version < "3"
